jformat/__init__.py
jformat/cli.py
jformat/cli_0.0.1.py
tests/__init__.py
tests/test_formatter.py
tests/test_jformat.py
jformat-0.0.4.dist-info/LICENSE
jformat-0.0.4.dist-info/METADATA
jformat-0.0.4.dist-info/WHEEL
jformat-0.0.4.dist-info/entry_points.txt
jformat-0.0.4.dist-info/top_level.txt
jformat-0.0.4.dist-info/RECORD
